anubis/__init__.py
anubis/__main__.py
anubis/arg_parser_main.py
anubis/feature_file_parser.py
anubis/parallelizer.py
anubis/results.py
anubis/text.py
bpp_anubis-2025.3.14.dist-info/LICENSE
bpp_anubis-2025.3.14.dist-info/METADATA
bpp_anubis-2025.3.14.dist-info/WHEEL
bpp_anubis-2025.3.14.dist-info/entry_points.txt
bpp_anubis-2025.3.14.dist-info/top_level.txt
bpp_anubis-2025.3.14.dist-info/RECORD
