Metadata-Version: 2.1
Name: bpp-anubis
Version: 2025.3.14
Summary: Run behave tests in parallel
Home-page: https://gitlab.com/blueprintprep/bpp-qa/utilities/anubis
Author: matthew bahloul
Author-email: matthew.bahloul@blueprintprep.com
License: MIT
Classifier: Development Status :: 4 - Beta
Classifier: License :: OSI Approved :: MIT License
Classifier: Programming Language :: Python :: 3.10
License-File: LICENSE
Requires-Dist: behave==1.2.6
